ict_auth/__init__.py
ict_auth/_version.py
ict_auth/ci_test.py
ict_auth/cli.py
ict_auth/core.py
ict_auth/logger.py
ict_auth/service.py
ict_auth/systemd.py
ict_auth/browser/.links/21b29af266f377fb687d56fd0b78a4e6ac072917
ict_auth/browser/chromium_headless_shell-1169/DEPENDENCIES_VALIDATED
ict_auth/browser/chromium_headless_shell-1169/INSTALLATION_COMPLETE
ict_auth/browser/chromium_headless_shell-1169/chrome-linux/headless_command_resources.pak
ict_auth/browser/chromium_headless_shell-1169/chrome-linux/headless_lib_data.pak
ict_auth/browser/chromium_headless_shell-1169/chrome-linux/headless_lib_strings.pak
ict_auth/browser/chromium_headless_shell-1169/chrome-linux/headless_shell
ict_auth/browser/chromium_headless_shell-1169/chrome-linux/icudtl.dat
ict_auth/browser/chromium_headless_shell-1169/chrome-linux/libEGL.so
ict_auth/browser/chromium_headless_shell-1169/chrome-linux/libGLESv2.so
ict_auth/browser/chromium_headless_shell-1169/chrome-linux/libvk_swiftshader.so
ict_auth/browser/chromium_headless_shell-1169/chrome-linux/libvulkan.so.1
ict_auth/browser/chromium_headless_shell-1169/chrome-linux/v8_context_snapshot.bin
ict_auth/browser/chromium_headless_shell-1169/chrome-linux/vk_swiftshader_icd.json
ict_auth/browser/ffmpeg-1011/COPYING.LGPLv2.1
ict_auth/browser/ffmpeg-1011/DEPENDENCIES_VALIDATED
ict_auth/browser/ffmpeg-1011/INSTALLATION_COMPLETE
ict_auth/browser/ffmpeg-1011/ffmpeg-linux
ict_auth/libs/libX11.so.6
ict_auth/libs/libXau.so.6
ict_auth/libs/libXcomposite.so.1
ict_auth/libs/libXdamage.so.1
ict_auth/libs/libXdmcp.so.6
ict_auth/libs/libXext.so.6
ict_auth/libs/libXfixes.so.3
ict_auth/libs/libXi.so.6
ict_auth/libs/libXrandr.so.2
ict_auth/libs/libXrender.so.1
ict_auth/libs/libasound.so.2
ict_auth/libs/libatk-1.0.so.0
ict_auth/libs/libatk-bridge-2.0.so.0
ict_auth/libs/libatspi.so.0
ict_auth/libs/libblkid.so.1
ict_auth/libs/libbsd.so.0
ict_auth/libs/libcap.so.2
ict_auth/libs/libdbus-1.so.3
ict_auth/libs/libdl.so.2
ict_auth/libs/libdrm.so.2
ict_auth-2.1.3.dist-info/METADATA
ict_auth-2.1.3.dist-info/WHEEL
ict_auth-2.1.3.dist-info/entry_points.txt
ict_auth-2.1.3.dist-info/RECORD
