Metadata-Version: 2.4
Name: ict-auth
Version: 2.1.3
Summary: 使用 CLI 进行中科院计算所上网认证登陆
Project-URL: Homepage, https://github.com/jklincn/ict_auth
Project-URL: Repository, https://github.com/jklincn/ict_auth
Author-email: jklincn <jklincn@outlook.com>
License-Expression: MIT
Requires-Python: >=3.9
Requires-Dist: playwright==1.52.0
Requires-Dist: typer==0.15.4
